sat/VERSION
sat/__init__.py
sat/bridge/__init__.py
sat/bridge/dbus_bridge.py
sat/bridge/pb.py
sat/bridge/bridge_constructor/__init__.py
sat/bridge/bridge_constructor/base_constructor.py
sat/bridge/bridge_constructor/bridge_constructor.py
sat/bridge/bridge_constructor/constants.py
sat/bridge/bridge_constructor/constructors/__init__.py
sat/bridge/bridge_constructor/constructors/dbus/__init__.py
sat/bridge/bridge_constructor/constructors/dbus/constructor.py
sat/bridge/bridge_constructor/constructors/dbus/dbus_core_template.py
sat/bridge/bridge_constructor/constructors/dbus/dbus_frontend_template.py
sat/bridge/bridge_constructor/constructors/dbus-xml/__init__.py
sat/bridge/bridge_constructor/constructors/dbus-xml/constructor.py
sat/bridge/bridge_constructor/constructors/embedded/__init__.py
sat/bridge/bridge_constructor/constructors/embedded/constructor.py
sat/bridge/bridge_constructor/constructors/embedded/embedded_frontend_template.py
sat/bridge/bridge_constructor/constructors/embedded/embedded_template.py
sat/bridge/bridge_constructor/constructors/mediawiki/__init__.py
sat/bridge/bridge_constructor/constructors/mediawiki/constructor.py
sat/bridge/bridge_constructor/constructors/pb/__init__.py
sat/bridge/bridge_constructor/constructors/pb/constructor.py
sat/bridge/bridge_constructor/constructors/pb/pb_core_template.py
sat/bridge/bridge_constructor/constructors/pb/pb_frontend_template.py
sat/core/__init__.py
sat/core/constants.py
sat/core/exceptions.py
sat/core/i18n.py
sat/core/log.py
sat/core/log_config.py
sat/core/patches.py
sat/core/sat_main.py
sat/core/xmpp.py
sat/memory/__init__.py
sat/memory/cache.py
sat/memory/crypto.py
sat/memory/disco.py
sat/memory/encryption.py
sat/memory/memory.py
sat/memory/params.py
sat/memory/persistent.py
sat/memory/sqlite.py
sat/plugins/__init__.py
sat/plugins/plugin_adhoc_dbus.py
sat/plugins/plugin_blog_import.py
sat/plugins/plugin_blog_import_dokuwiki.py
sat/plugins/plugin_blog_import_dotclear.py
sat-0.7.0.dist-info/COPYING
sat-0.7.0.dist-info/METADATA
sat-0.7.0.dist-info/WHEEL
sat-0.7.0.dist-info/top_level.txt
sat-0.7.0.dist-info/RECORD
