Metadata-Version: 2.1
Name: sat
Version: 0.7.0
Summary: Salut à Toi multipurpose and multi frontend XMPP client
Home-page: https://salut-a-toi.org
Author: Association « Salut à Toi »
Author-email: contact@goffi.org
License: UNKNOWN
Platform: UNKNOWN
Classifier: Development Status :: 3 - Alpha
Classifier: Environment :: Console
Classifier: Framework :: Twisted
Classifier: License :: OSI Approved :: GNU Affero General Public License v3 or later (AGPLv3+)
Classifier: Operating System :: POSIX :: Linux
Classifier: Topic :: Communications :: Chat
Requires-Python: ~=2.7
Requires-Dist: babel
Requires-Dist: dbus-python
Requires-Dist: html2text
Requires-Dist: jinja2 (>=2.10)
Requires-Dist: langid
Requires-Dist: lxml (>=3.1.0)
Requires-Dist: markdown (>=3.0)
Requires-Dist: miniupnpc
Requires-Dist: mutagen
Requires-Dist: netifaces
Requires-Dist: pillow
Requires-Dist: progressbar
Requires-Dist: pycrypto (>=2.6.1)
Requires-Dist: pygments
Requires-Dist: pygobject
Requires-Dist: PyOpenSSL
Requires-Dist: python-dateutil
Requires-Dist: python-potr
Requires-Dist: pyxdg
Requires-Dist: sat-tmp (>=0.7.0a4)
Requires-Dist: shortuuid
Requires-Dist: twisted[tls] (>=15.2.0)
Requires-Dist: urwid (>=1.2.0)
Requires-Dist: urwid-satext (>=0.7.0a2)
Requires-Dist: wokkel (>=0.7.1)
Requires-Dist: omemo
Requires-Dist: omemo-backend-signal
